zoko/__about__.py
zoko/__init__.py
zoko/client.py
zoko/constants/__init__.py
zoko/constants/endpoint.py
zoko/resources/__init__.py
zoko/resources/account.py
zoko/resources/message.py
zoko/types/common.py
zoko-0.0.1.dist-info/LICENSE.txt
zoko-0.0.1.dist-info/METADATA
zoko-0.0.1.dist-info/WHEEL
zoko-0.0.1.dist-info/top_level.txt
zoko-0.0.1.dist-info/RECORD
