Metadata-Version: 2.1
Name: zoko
Version: 0.0.1
Summary: Python SDK for Zoko API
Author-email: Rocktim Saikia <rocktimthedev@gmail.com>
Project-URL: homepage, https://github.com/rocktimsaikia/zoko-python
Project-URL: repository, https://github.com/rocktimsaikia/zoko-python
Project-URL: issues, https://github.com/rocktimsaikia/zoko-python/issues
Keywords: zoko,api,sdk,python,library
Classifier: Development Status :: 3 - Alpha
Classifier: Intended Audience :: Developers
Classifier: License :: OSI Approved :: MIT License
Classifier: Programming Language :: Python :: 3
Classifier: Programming Language :: Python :: 3.8
Classifier: Programming Language :: Python :: 3.9
Classifier: Programming Language :: Python :: 3.10
Requires-Python: >=3.8
License-File: LICENSE.txt
Requires-Dist: requests
